{
  "circles": {
    "1": {
      "left": 6.0,
      "top": 6.0
    },
    "2": {
      "left": 36.0,
      "top": 6.0
    },
    "3": {
      "left": 37.0,
      "top": 621.0
    },
    "4": {
      "left": 67.0,
      "top": 6.0
    },
    "5": {
      "left": 68.0,
      "top": 621.0
    },
    "6": {
      "left": 96.0,
      "top": 6.0
    },
    "7": {
      "left": 97.0,
      "top": 621.0
    },
    "8": {
      "left": 125.0,
      "top": 6.0
    },
    "9": {
      "left": 126.0,
      "top": 621.0
    },
    "10": {
      "left": 154.0,
      "top": 6.0
    },
    "11": {
      "left": 155.0,
      "top": 621.0
    },
    "12": {
      "left": 183.0,
      "top": 6.0
    },
    "13": {
      "left": 184.0,
      "top": 621.0
    },
    "14": {
      "left": 212.0,
      "top": 6.0
    },
    "15": {
      "left": 213.0,
      "top": 621.0
    },
    "16": {
      "left": 241.0,
      "top": 6.0
    },
    "17": {
      "left": 242.0,
      "top": 621.0
    },
    "18": {
      "left": 5.0,
      "top": 590.0
    },
    "19": {
      "left": 5.0,
      "top": 621.0
    },
    "20": {
      "left": 622.0,
      "top": 621.0
    },
    "21": {
      "left": 622.0,
      "top": 592.0
    },
    "22": {
      "left": 622.0,
      "top": 102.0
    },
    "23": {
      "left": 6.0,
      "top": 132.0
    },
    "24": {
      "left": 622.0,
      "top": 133.0
    },
    "25": {
      "left": 6.0,
      "top": 163.0
    },
    "26": {
      "left": 622.0,
      "top": 164.0
    },
    "27": {
      "left": 6.0,
      "top": 194.0
    },
    "28": {
      "left": 622.0,
      "top": 195.0
    },
    "29": {
      "left": 6.0,
      "top": 225.0
    },
    "30": {
      "left": 622.0,
      "top": 226.0
    },
    "31": {
      "left": 6.0,
      "top": 256.0
    },
    "32": {
      "left": 622.0,
      "top": 257.0
    },
    "33": {
      "left": 6.0,
      "top": 287.0
    },
    "34": {
      "left": 622.0,
      "top": 288.0
    },
    "35": {
      "left": 6.0,
      "top": 318.0
    },
    "36": {
      "left": 622.0,
      "top": 319.0
    },
    "37": {
      "left": 6.0,
      "top": 349.0
    },
    "38": {
      "left": 622.0,
      "top": 350.0
    },
    "39": {
      "left": 6.0,
      "top": 380.0
    },
    "40": {
      "left": 622.0,
      "top": 381.0
    },
    "41": {
      "left": 622.0,
      "top": 412.0
    },
    "42": {
      "left": 622.0,
      "top": 443.0
    },
    "43": {
      "left": 622.0,
      "top": 474.0
    },
    "44": {
      "left": 622.0,
      "top": 505.0
    },
    "45": {
      "left": 622.0,
      "top": 536.0
    },
    "46": {
      "left": 5.0,
      "top": 411.0
    },
    "47": {
      "left": 5.0,
      "top": 442.0
    },
    "48": {
      "left": 5.0,
      "top": 473.0
    },
    "49": {
      "left": 5.0,
      "top": 504.0
    },
    "50": {
      "left": 5.0,
      "top": 535.0
    },
    "51": {
      "left": 5.0,
      "top": 561.0
    },
    "52": {
      "left": 622.0,
      "top": 563.0
    },
    "53": {
      "left": 270.0,
      "top": 6.0
    },
    "54": {
      "left": 271.0,
      "top": 621.0
    },
    "55": {
      "left": 299.0,
      "top": 6.0
    },
    "56": {
      "left": 300.0,
      "top": 621.0
    },
    "57": {
      "left": 328.0,
      "top": 6.0
    },
    "58": {
      "left": 329.0,
      "top": 621.0
    },
    "59": {
      "left": 357.0,
      "top": 6.0
    },
    "60": {
      "left": 358.0,
      "top": 621.0
    },
    "61": {
      "left": 386.0,
      "top": 6.0
    },
    "62": {
      "left": 387.0,
      "top": 621.0
    },
    "63": {
      "left": 415.0,
      "top": 6.0
    },
    "64": {
      "left": 416.0,
      "top": 621.0
    },
    "65": {
      "left": 444.0,
      "top": 6.0
    },
    "66": {
      "left": 445.0,
      "top": 621.0
    },
    "67": {
      "left": 473.0,
      "top": 6.0
    },
    "68": {
      "left": 474.0,
      "top": 621.0
    },
    "69": {
      "left": 502.0,
      "top": 6.0
    },
    "70": {
      "left": 503.0,
      "top": 621.0
    },
    "71": {
      "left": 531.0,
      "top": 6.0
    },
    "72": {
      "left": 532.0,
      "top": 621.0
    },
    "73": {
      "left": 560.0,
      "top": 6.0
    },
    "74": {
      "left": 561.0,
      "top": 621.0
    },
    "75": {
      "left": 589.0,
      "top": 6.0
    },
    "76": {
      "left": 590.0,
      "top": 621.0
    },
    "77": {
      "left": 622.0,
      "top": 6.0
    },
    "78": {
      "left": 6.0,
      "top": 39.0
    },
    "79": {
      "left": 622.0,
      "top": 40.0
    },
    "80": {
      "left": 6.0,
      "top": 70.0
    },
    "81": {
      "left": 622.0,
      "top": 71.0
    },
    "82": {
      "left": 6.0,
      "top": 101.0
    }
  },
  "squares": {
    "1": {
      "left": 549.0,
      "top": 0.0
    },
    "2": {
      "left": 510.0,
      "top": 0.0
    },
    "3": {
      "left": 471.0,
      "top": 0.0
    },
    "4": {
      "left": 432.0,
      "top": 0.0
    },
    "5": {
      "left": 393.0,
      "top": 0.0
    },
    "6": {
      "left": 354.0,
      "top": 0.0
    },
    "7": {
      "left": 315.0,
      "top": 0.0
    },
    "8": {
      "left": 276.0,
      "top": 0.0
    },
    "9": {
      "left": 237.0,
      "top": 0.0
    },
    "10": {
      "left": 198.0,
      "top": 0.0
    },
    "11": {
      "left": 159.0,
      "top": 0.0
    },
    "12": {
      "left": 120.0,
      "top": 0.0
    },
    "13": {
      "left": 81.0,
      "top": 0.0
    },
    "14": {
      "left": 42.0,
      "top": 0.0
    },
    "15": {
      "left": 3.0,
      "top": 0.0
    },
    "16": {
      "left": 549.0,
      "top": 39.0
    },
    "17": {
      "left": 510.0,
      "top": 39.0
    },
    "18": {
      "left": 471.0,
      "top": 39.0
    },
    "19": {
      "left": 432.0,
      "top": 39.0
    },
    "20": {
      "left": 393.0,
      "top": 39.0
    },
    "21": {
      "left": 354.0,
      "top": 39.0
    },
    "22": {
      "left": 315.0,
      "top": 39.0
    },
    "23": {
      "left": 276.0,
      "top": 39.0
    },
    "24": {
      "left": 237.0,
      "top": 39.0
    },
    "25": {
      "left": 198.0,
      "top": 39.0
    },
    "26": {
      "left": 159.0,
      "top": 39.0
    },
    "27": {
      "left": 120.0,
      "top": 39.0
    },
    "28": {
      "left": 81.0,
      "top": 39.0
    },
    "29": {
      "left": 42.0,
      "top": 39.0
    },
    "30": {
      "left": 3.0,
      "top": 39.0
    },
    "31": {
      "left": 549.0,
      "top": 78.0
    },
    "32": {
      "left": 510.0,
      "top": 78.0
    },
    "33": {
      "left": 471.0,
      "top": 78.0
    },
    "34": {
      "left": 432.0,
      "top": 78.0
    },
    "35": {
      "left": 393.0,
      "top": 78.0
    },
    "36": {
      "left": 354.0,
      "top": 78.0
    },
    "37": {
      "left": 315.0,
      "top": 78.0
    },
    "38": {
      "left": 276.0,
      "top": 78.0
    },
    "39": {
      "left": 237.0,
      "top": 78.0
    },
    "40": {
      "left": 198.0,
      "top": 78.0
    },
    "41": {
      "left": 159.0,
      "top": 78.0
    },
    "42": {
      "left": 120.0,
      "top": 78.0
    },
    "43": {
      "left": 81.0,
      "top": 78.0
    },
    "44": {
      "left": 42.0,
      "top": 78.0
    },
    "45": {
      "left": 3.0,
      "top": 78.0
    },
    "46": {
      "left": 549.0,
      "top": 117.0
    },
    "47": {
      "left": 510.0,
      "top": 117.0
    },
    "48": {
      "left": 471.0,
      "top": 117.0
    },
    "49": {
      "left": 432.0,
      "top": 117.0
    },
    "50": {
      "left": 393.0,
      "top": 117.0
    },
    "51": {
      "left": 354.0,
      "top": 117.0
    },
    "52": {
      "left": 315.0,
      "top": 117.0
    },
    "53": {
      "left": 276.0,
      "top": 117.0
    },
    "54": {
      "left": 237.0,
      "top": 117.0
    },
    "55": {
      "left": 198.0,
      "top": 117.0
    },
    "56": {
      "left": 159.0,
      "top": 117.0
    },
    "57": {
      "left": 120.0,
      "top": 117.0
    },
    "58": {
      "left": 81.0,
      "top": 117.0
    },
    "59": {
      "left": 42.0,
      "top": 117.0
    },
    "60": {
      "left": 3.0,
      "top": 117.0
    },
    "61": {
      "left": 549.0,
      "top": 156.0
    },
    "62": {
      "left": 510.0,
      "top": 156.0
    },
    "63": {
      "left": 471.0,
      "top": 156.0
    },
    "64": {
      "left": 432.0,
      "top": 156.0
    },
    "65": {
      "left": 393.0,
      "top": 156.0
    },
    "66": {
      "left": 354.0,
      "top": 156.0
    },
    "67": {
      "left": 315.0,
      "top": 156.0
    },
    "68": {
      "left": 276.0,
      "top": 156.0
    },
    "69": {
      "left": 237.0,
      "top": 156.0
    },
    "70": {
      "left": 198.0,
      "top": 156.0
    },
    "71": {
      "left": 159.0,
      "top": 156.0
    },
    "72": {
      "left": 120.0,
      "top": 156.0
    },
    "73": {
      "left": 81.0,
      "top": 156.0
    },
    "74": {
      "left": 42.0,
      "top": 156.0
    },
    "75": {
      "left": 3.0,
      "top": 156.0
    },
    "76": {
      "left": 549.0,
      "top": 195.0
    },
    "77": {
      "left": 510.0,
      "top": 195.0
    },
    "78": {
      "left": 471.0,
      "top": 195.0
    },
    "79": {
      "left": 432.0,
      "top": 195.0
    },
    "80": {
      "left": 393.0,
      "top": 195.0
    },
    "81": {
      "left": 354.0,
      "top": 195.0
    },
    "82": {
      "left": 315.0,
      "top": 195.0
    },
    "83": {
      "left": 276.0,
      "top": 195.0
    },
    "84": {
      "left": 237.0,
      "top": 195.0
    },
    "85": {
      "left": 198.0,
      "top": 195.0
    },
    "86": {
      "left": 159.0,
      "top": 195.0
    },
    "87": {
      "left": 120.0,
      "top": 195.0
    },
    "88": {
      "left": 81.0,
      "top": 195.0
    },
    "89": {
      "left": 42.0,
      "top": 195.0
    },
    "90": {
      "left": 3.0,
      "top": 195.0
    },
    "91": {
      "left": 549.0,
      "top": 234.0
    },
    "92": {
      "left": 510.0,
      "top": 234.0
    },
    "93": {
      "left": 471.0,
      "top": 234.0
    },
    "94": {
      "left": 432.0,
      "top": 234.0
    },
    "95": {
      "left": 393.0,
      "top": 234.0
    },
    "96": {
      "left": 354.0,
      "top": 234.0
    },
    "97": {
      "left": 315.0,
      "top": 234.0
    },
    "98": {
      "left": 276.0,
      "top": 234.0
    },
    "99": {
      "left": 237.0,
      "top": 234.0
    },
    "100": {
      "left": 198.0,
      "top": 234.0
    },
    "101": {
      "left": 159.0,
      "top": 234.0
    },
    "102": {
      "left": 120.0,
      "top": 234.0
    },
    "103": {
      "left": 81.0,
      "top": 234.0
    },
    "104": {
      "left": 42.0,
      "top": 234.0
    },
    "105": {
      "left": 3.0,
      "top": 234.0
    },
    "106": {
      "left": 549.0,
      "top": 273.0
    },
    "107": {
      "left": 510.0,
      "top": 273.0
    },
    "108": {
      "left": 471.0,
      "top": 273.0
    },
    "109": {
      "left": 432.0,
      "top": 273.0
    },
    "110": {
      "left": 393.0,
      "top": 273.0
    },
    "111": {
      "left": 354.0,
      "top": 273.0
    },
    "112": {
      "left": 315.0,
      "top": 273.0
    },
    "113": {
      "left": 276.0,
      "top": 273.0
    },
    "114": {
      "left": 237.0,
      "top": 273.0
    },
    "115": {
      "left": 198.0,
      "top": 273.0
    },
    "116": {
      "left": 159.0,
      "top": 273.0
    },
    "117": {
      "left": 120.0,
      "top": 273.0
    },
    "118": {
      "left": 81.0,
      "top": 273.0
    },
    "119": {
      "left": 42.0,
      "top": 273.0
    },
    "120": {
      "left": 3.0,
      "top": 273.0
    },
    "121": {
      "left": 549.0,
      "top": 312.0
    },
    "122": {
      "left": 510.0,
      "top": 312.0
    },
    "123": {
      "left": 471.0,
      "top": 312.0
    },
    "124": {
      "left": 432.0,
      "top": 312.0
    },
    "125": {
      "left": 393.0,
      "top": 312.0
    },
    "126": {
      "left": 354.0,
      "top": 312.0
    },
    "127": {
      "left": 315.0,
      "top": 312.0
    },
    "128": {
      "left": 276.0,
      "top": 312.0
    },
    "129": {
      "left": 237.0,
      "top": 312.0
    },
    "130": {
      "left": 198.0,
      "top": 312.0
    },
    "131": {
      "left": 159.0,
      "top": 312.0
    },
    "132": {
      "left": 120.0,
      "top": 312.0
    },
    "133": {
      "left": 81.0,
      "top": 312.0
    },
    "134": {
      "left": 42.0,
      "top": 312.0
    },
    "135": {
      "left": 3.0,
      "top": 312.0
    },
    "136": {
      "left": 549.0,
      "top": 351.0
    },
    "137": {
      "left": 510.0,
      "top": 351.0
    },
    "138": {
      "left": 471.0,
      "top": 351.0
    },
    "139": {
      "left": 432.0,
      "top": 351.0
    },
    "140": {
      "left": 393.0,
      "top": 351.0
    },
    "141": {
      "left": 354.0,
      "top": 351.0
    },
    "142": {
      "left": 315.0,
      "top": 351.0
    },
    "143": {
      "left": 276.0,
      "top": 351.0
    },
    "144": {
      "left": 237.0,
      "top": 351.0
    },
    "145": {
      "left": 198.0,
      "top": 351.0
    },
    "146": {
      "left": 159.0,
      "top": 351.0
    },
    "147": {
      "left": 120.0,
      "top": 351.0
    },
    "148": {
      "left": 81.0,
      "top": 351.0
    },
    "149": {
      "left": 42.0,
      "top": 351.0
    },
    "150": {
      "left": 3.0,
      "top": 351.0
    },
    "151": {
      "left": 549.0,
      "top": 390.0
    },
    "152": {
      "left": 510.0,
      "top": 390.0
    },
    "153": {
      "left": 471.0,
      "top": 390.0
    },
    "154": {
      "left": 432.0,
      "top": 390.0
    },
    "155": {
      "left": 393.0,
      "top": 390.0
    },
    "156": {
      "left": 354.0,
      "top": 390.0
    },
    "157": {
      "left": 315.0,
      "top": 390.0
    },
    "158": {
      "left": 276.0,
      "top": 390.0
    },
    "159": {
      "left": 237.0,
      "top": 390.0
    },
    "160": {
      "left": 198.0,
      "top": 390.0
    },
    "161": {
      "left": 159.0,
      "top": 390.0
    },
    "162": {
      "left": 120.0,
      "top": 390.0
    },
    "163": {
      "left": 81.0,
      "top": 390.0
    },
    "164": {
      "left": 42.0,
      "top": 390.0
    },
    "165": {
      "left": 3.0,
      "top": 390.0
    },
    "166": {
      "left": 549.0,
      "top": 429.0
    },
    "167": {
      "left": 510.0,
      "top": 429.0
    },
    "168": {
      "left": 471.0,
      "top": 429.0
    },
    "169": {
      "left": 432.0,
      "top": 429.0
    },
    "170": {
      "left": 393.0,
      "top": 429.0
    },
    "171": {
      "left": 354.0,
      "top": 429.0
    },
    "172": {
      "left": 315.0,
      "top": 429.0
    },
    "173": {
      "left": 276.0,
      "top": 429.0
    },
    "174": {
      "left": 237.0,
      "top": 429.0
    },
    "175": {
      "left": 198.0,
      "top": 429.0
    },
    "176": {
      "left": 159.0,
      "top": 429.0
    },
    "177": {
      "left": 120.0,
      "top": 429.0
    },
    "178": {
      "left": 81.0,
      "top": 429.0
    },
    "179": {
      "left": 42.0,
      "top": 429.0
    },
    "180": {
      "left": 3.0,
      "top": 429.0
    },
    "181": {
      "left": 549.0,
      "top": 468.0
    },
    "182": {
      "left": 510.0,
      "top": 468.0
    },
    "183": {
      "left": 471.0,
      "top": 468.0
    },
    "184": {
      "left": 432.0,
      "top": 468.0
    },
    "185": {
      "left": 393.0,
      "top": 468.0
    },
    "186": {
      "left": 354.0,
      "top": 468.0
    },
    "187": {
      "left": 315.0,
      "top": 468.0
    },
    "188": {
      "left": 276.0,
      "top": 468.0
    },
    "189": {
      "left": 237.0,
      "top": 468.0
    },
    "190": {
      "left": 198.0,
      "top": 468.0
    },
    "191": {
      "left": 159.0,
      "top": 468.0
    },
    "192": {
      "left": 120.0,
      "top": 468.0
    },
    "193": {
      "left": 81.0,
      "top": 468.0
    },
    "194": {
      "left": 42.0,
      "top": 468.0
    },
    "195": {
      "left": 3.0,
      "top": 468.0
    },
    "196": {
      "left": 549.0,
      "top": 507.0
    },
    "197": {
      "left": 510.0,
      "top": 507.0
    },
    "198": {
      "left": 471.0,
      "top": 507.0
    },
    "199": {
      "left": 432.0,
      "top": 507.0
    },
    "200": {
      "left": 393.0,
      "top": 507.0
    },
    "201": {
      "left": 354.0,
      "top": 507.0
    },
    "202": {
      "left": 315.0,
      "top": 507.0
    },
    "203": {
      "left": 276.0,
      "top": 507.0
    },
    "204": {
      "left": 237.0,
      "top": 507.0
    },
    "205": {
      "left": 198.0,
      "top": 507.0
    },
    "206": {
      "left": 159.0,
      "top": 507.0
    },
    "207": {
      "left": 120.0,
      "top": 507.0
    },
    "208": {
      "left": 81.0,
      "top": 507.0
    },
    "209": {
      "left": 42.0,
      "top": 507.0
    },
    "210": {
      "left": 3.0,
      "top": 507.0
    },
    "211": {
      "left": 549.0,
      "top": 546.0
    },
    "212": {
      "left": 510.0,
      "top": 546.0
    },
    "213": {
      "left": 471.0,
      "top": 546.0
    },
    "214": {
      "left": 432.0,
      "top": 546.0
    },
    "215": {
      "left": 393.0,
      "top": 546.0
    },
    "216": {
      "left": 354.0,
      "top": 546.0
    },
    "217": {
      "left": 315.0,
      "top": 546.0
    },
    "218": {
      "left": 276.0,
      "top": 546.0
    },
    "219": {
      "left": 237.0,
      "top": 546.0
    },
    "220": {
      "left": 198.0,
      "top": 546.0
    },
    "221": {
      "left": 159.0,
      "top": 546.0
    },
    "222": {
      "left": 120.0,
      "top": 546.0
    },
    "223": {
      "left": 81.0,
      "top": 546.0
    },
    "224": {
      "left": 42.0,
      "top": 546.0
    },
    "225": {
      "left": 3.0,
      "top": 546.0
    }
  }
}